globus_etl_utils/__init__.py
globus_etl_utils/backend_candidates_service.py
globus_etl_utils/backend_service.py
globus_etl_utils/config_reader.py
globus_etl_utils/job.py
globus_etl_utils/json.py
globus_etl_utils/persistance_service.py
globus_etl_utils/pipeline.py
globus_etl_utils/recman_service.py
globus_etl_utils/spark.py
globus_etl_utils/spark_job.py
globus_etl_utils/tenant_aware_job.py
globus_etl_utils/tenant_aware_spark_job.py
globus_etl_utils/tenant_service.py
globus_etl_utils/utils.py
globus.etl.utils-0.0.3.dist-info/METADATA
globus.etl.utils-0.0.3.dist-info/WHEEL
globus.etl.utils-0.0.3.dist-info/top_level.txt
globus.etl.utils-0.0.3.dist-info/RECORD
