Metadata-Version: 2.1
Name: globus.etl.utils
Version: 0.0.3
Summary: ETL tools for Globus Staffing
Home-page: https://bitbucket.org/dedicare/globus_etl_utils/src/develop/
Author: globus.ai
Author-email: zhas@globus.ai
License: MIT
Download-URL: https://pypi.org/project/globusetlutils/
Keywords: Staffing,ETL
Platform: UNKNOWN
Requires-Dist: pytz (>=2019.3)
Requires-Dist: pyodbc (>=4.0.30)
Requires-Dist: pymongo (>=3.8.0)
Requires-Dist: requests (>=2.23.0)
Requires-Dist: azure-storage-blob (>=0.37.0)
Requires-Dist: pyspark (>=3.0.0)
Requires-Dist: python-dateutil (>=2.8.1)
